{"type":"article_comment","id":15144,"parentType":"article","parentId":2194,"uid":7159,"contents":"2020/06/20<br>\n<a href=\"https://t.me/Ruters0615/1806\" rel=\"nofollow noreferrer noopener\" target=\"_blank\">原文链接</a><br>\n<blockquote>爱国买卖<br>\n曲：爱情买卖<br>\n<br>\n出卖我的爱 把我当韭菜<br>\n最后知道真相的我眼泪掉下来<br>\n出卖我的爱 你背了良心债<br>\n就算打上再多鸡血也再买不回来<br>\n当初是你割韭菜 应该不应该<br>\n现在又要用口嗨把我哄回来<br>\n爱国不是你想卖 想买就能卖<br>\n让我疑猜 让我明白 不配我去爱<br>\n<br>\n<br>\n说唱：出卖你的爱 把你当韭菜<br>\n全靠痛苦的你我的荷包才鼓起来<br>\n出卖你的爱 你背了车房贷<br>\n就算打上再多鸡血也再买不回来<br>\n虽然当初是我割韭菜 后来才明白<br>\n现在我用我的权力希望韭菜生出来<br>\n我明白是我错了 爱国像你说的<br>\n它不是买卖就算千金来买都不卖<br>\n<br>\n<br>\n出卖我的爱 把我当韭菜<br>\n最后知道真相的我眼泪掉下来<br>\n出卖我的爱 你背了良心债<br>\n就算打上再多鸡血也再买不回来<br>\n当初是你割韭菜 应该不应该<br>\n现在又要用口嗨把我哄回来<br>\n爱国不是你想卖 想买就能卖<br>\n让我疑猜 让我明白 不配我去爱<br>\n铁拳把我来伤害 爱这么意外<br>\n单纯朴素的热爱 受伤才明白<br>\n爱国不是你想买 想买就能买<br>\n让我看透 痴心的人 不配有真爱<br>\n当初是你割韭菜 应该不应该<br>\n现在又要用口嗨把我哄回来<br>\n爱国不是你想卖 想买就能卖<br>\n让我疑猜 让我明白 不配我去爱</blockquote>","date":"2020-06-20","agreeCount":0,"discussionCount":0}