{"type":"article","id":1993,"title":"【翻车新闻修复计划】vol 282-284：b站有人公开对线共青团？&转发之前记得看id啊&电影解说竟敢影射今上！？","uid":4611,"topics":[584,2714],"contents":"原址：282：<a href=\"https://www.reddit.com/r/hanren/comments/frj86i\" rel=\"nofollow noreferrer noopener\" target=\"_blank\">https://www.reddit.com/r/hanren/comments/frj86i</a><br>\n283：<a href=\"https://www.reddit.com/r/hanren/comments/fs72ec\" rel=\"nofollow noreferrer noopener\" target=\"_blank\">https://www.reddit.com/r/hanren/comments/fs72ec</a><br>\n284：<a href=\"https://www.reddit.com/r/hanren/comments/fs7sck\" rel=\"nofollow noreferrer noopener\" target=\"_blank\">https://www.reddit.com/r/hanren/comments/fs7sck</a><br>\n<br>\n<br>\n<br>\n【翻车新闻】vol 282：b站有人公开对线共青团？<br>\n<br>\n1 优质财经内容？<br>\n<br>\n<a href=\"https://i.redd.it/5r7x84x86qp41.jpg\" rel=\"nofollow noreferrer noopener\" target=\"_blank\"><img src=\"https://i.redd.it/5r7x84x86qp41.jpg\" alt=\"https://i.redd.it/5r7x84x86qp41.jpg\" style=\"max-width:100%\"></a><br>\n2 大 学 问<br>\n<br>\n<a href=\"https://i.redd.it/api5j7y86qp41.jpg\" rel=\"nofollow noreferrer noopener\" target=\"_blank\"><img src=\"https://i.redd.it/api5j7y86qp41.jpg\" alt=\"https://i.redd.it/api5j7y86qp41.jpg\" style=\"max-width:100%\"></a><br>\n3 ？？？<br>\n<br>\n<a href=\"https://i.redd.it/o69u3tw86qp41.jpg\" rel=\"nofollow noreferrer noopener\" target=\"_blank\"><img src=\"https://i.redd.it/o69u3tw86qp41.jpg\" alt=\"https://i.redd.it/o69u3tw86qp41.jpg\" style=\"max-width:100%\"></a><br>\n4 接龙整理文件<br>\n<br>\n<a href=\"https://i.redd.it/agm9hg096qp41.jpg\" rel=\"nofollow noreferrer noopener\" target=\"_blank\"><img src=\"https://i.redd.it/agm9hg096qp41.jpg\" alt=\"https://i.redd.it/agm9hg096qp41.jpg\" style=\"max-width:100%\"></a><br>\n5 真积极啊<br>\n<br>\n<a href=\"https://i.redd.it/y75rx8x86qp41.jpg\" rel=\"nofollow noreferrer noopener\" target=\"_blank\"><img src=\"https://i.redd.it/y75rx8x86qp41.jpg\" alt=\"https://i.redd.it/y75rx8x86qp41.jpg\" style=\"max-width:100%\"></a><br>\n6 洗地学<br>\n<br>\n<a href=\"https://i.redd.it/ljtgzcx86qp41.jpg\" rel=\"nofollow noreferrer noopener\" target=\"_blank\"><img src=\"https://i.redd.it/ljtgzcx86qp41.jpg\" alt=\"https://i.redd.it/ljtgzcx86qp41.jpg\" style=\"max-width:100%\"></a><br>\n7 谁说我们不发钱的！<br>\n<br>\n<a href=\"https://i.redd.it/xvjcwfx86qp41.jpg\" rel=\"nofollow noreferrer noopener\" target=\"_blank\"><img src=\"https://i.redd.it/xvjcwfx86qp41.jpg\" alt=\"https://i.redd.it/xvjcwfx86qp41.jpg\" style=\"max-width:100%\"></a><br>\n8 原来如此<br>\n<br>\n<a href=\"https://i.redd.it/avizifx86qp41.jpg\" rel=\"nofollow noreferrer noopener\" target=\"_blank\"><img src=\"https://i.redd.it/avizifx86qp41.jpg\" alt=\"https://i.redd.it/avizifx86qp41.jpg\" style=\"max-width:100%\"></a><br>\n9 豆瓣收藏夹<br>\n<br>\n<a href=\"https://i.redd.it/8904llx86qp41.jpg\" rel=\"nofollow noreferrer noopener\" target=\"_blank\"><img src=\"https://i.redd.it/8904llx86qp41.jpg\" alt=\"https://i.redd.it/8904llx86qp41.jpg\" style=\"max-width:100%\"></a><br>\n10 尤里训练中心<br>\n<br>\n<a href=\"https://i.redd.it/k470pg096qp41.jpg\" rel=\"nofollow noreferrer noopener\" target=\"_blank\"><img src=\"https://i.redd.it/k470pg096qp41.jpg\" alt=\"https://i.redd.it/k470pg096qp41.jpg\" style=\"max-width:100%\"></a><br>\n11 b站不要命大师<br>\n<br>\n<a href=\"https://i.redd.it/1w9d71x86qp41.jpg\" rel=\"nofollow noreferrer noopener\" target=\"_blank\"><img src=\"https://i.redd.it/1w9d71x86qp41.jpg\" alt=\"https://i.redd.it/1w9d71x86qp41.jpg\" style=\"max-width:100%\"></a><br>\n<a href=\"https://i.redd.it/8acn4px86qp41.jpg\" rel=\"nofollow noreferrer noopener\" target=\"_blank\"><img src=\"https://i.redd.it/8acn4px86qp41.jpg\" alt=\"https://i.redd.it/8acn4px86qp41.jpg\" style=\"max-width:100%\"></a><br>\n<a href=\"https://i.redd.it/rfj3fzw86qp41.jpg\" rel=\"nofollow noreferrer noopener\" target=\"_blank\"><img src=\"https://i.redd.it/rfj3fzw86qp41.jpg\" alt=\"https://i.redd.it/rfj3fzw86qp41.jpg\" style=\"max-width:100%\"></a><br>\n<a href=\"https://i.redd.it/a84eu0x86qp41.jpg\" rel=\"nofollow noreferrer noopener\" target=\"_blank\"><img src=\"https://i.redd.it/a84eu0x86qp41.jpg\" alt=\"https://i.redd.it/a84eu0x86qp41.jpg\" style=\"max-width:100%\"></a><br>\n12 求仁得仁小粉红<br>\n<br>\n<a href=\"https://i.redd.it/biorm0y86qp41.jpg\" rel=\"nofollow noreferrer noopener\" target=\"_blank\"><img src=\"https://i.redd.it/biorm0y86qp41.jpg\" alt=\"https://i.redd.it/biorm0y86qp41.jpg\" style=\"max-width:100%\"></a><br>\n13 恶臭管理员<br>\n<br>\n<a href=\"https://i.redd.it/7juf58y86qp41.jpg\" rel=\"nofollow noreferrer noopener\" target=\"_blank\"><img src=\"https://i.redd.it/7juf58y86qp41.jpg\" alt=\"https://i.redd.it/7juf58y86qp41.jpg\" style=\"max-width:100%\"></a><br>\n14 双标大师<br>\n<br>\n<a href=\"https://i.redd.it/4kucs8y86qp41.png\" rel=\"nofollow noreferrer noopener\" target=\"_blank\"><img src=\"https://i.redd.it/4kucs8y86qp41.png\" alt=\"https://i.redd.it/4kucs8y86qp41.png\" style=\"max-width:100%\"></a><br>\n<br>\n<br>\n【翻车新闻】vol 283：转发之前记得看id啊<br>\n<br>\n1 那位对线共青团的老哥原来也。。。<br>\n<br>\n<a href=\"https://i.redd.it/5vefqtsxzxp41.jpg\" rel=\"nofollow noreferrer noopener\" target=\"_blank\"><img src=\"https://i.redd.it/5vefqtsxzxp41.jpg\" alt=\"https://i.redd.it/5vefqtsxzxp41.jpg\" style=\"max-width:100%\"></a><br>\n2 <mark>支</mark>持一个，这种电影实在不多见了<br>\n<br>\n<a href=\"https://i.redd.it/926pa4txzxp41.jpg\" rel=\"nofollow noreferrer noopener\" target=\"_blank\"><img src=\"https://i.redd.it/926pa4txzxp41.jpg\" alt=\"https://i.redd.it/926pa4txzxp41.jpg\" style=\"max-width:100%\"></a><br>\n<a href=\"https://i.redd.it/yekbgcwxzxp41.jpg\" rel=\"nofollow noreferrer noopener\" target=\"_blank\"><img src=\"https://i.redd.it/yekbgcwxzxp41.jpg\" alt=\"https://i.redd.it/yekbgcwxzxp41.jpg\" style=\"max-width:100%\"></a><br>\n3 国师对线<br>\n<br>\n<a href=\"https://i.redd.it/iybon2txzxp41.jpg\" rel=\"nofollow noreferrer noopener\" target=\"_blank\"><img src=\"https://i.redd.it/iybon2txzxp41.jpg\" alt=\"https://i.redd.it/iybon2txzxp41.jpg\" style=\"max-width:100%\"></a><br>\n<a href=\"https://i.redd.it/mp8xgmtxzxp41.jpg\" rel=\"nofollow noreferrer noopener\" target=\"_blank\"><img src=\"https://i.redd.it/mp8xgmtxzxp41.jpg\" alt=\"https://i.redd.it/mp8xgmtxzxp41.jpg\" style=\"max-width:100%\"></a><br>\n4 全部枪毙<br>\n<br>\n<a href=\"https://i.redd.it/avjxh6wxzxp41.jpg\" rel=\"nofollow noreferrer noopener\" target=\"_blank\"><img src=\"https://i.redd.it/avjxh6wxzxp41.jpg\" alt=\"https://i.redd.it/avjxh6wxzxp41.jpg\" style=\"max-width:100%\"></a><br>\n5 手冲左人<br>\n<br>\n<a href=\"https://i.redd.it/s9m5xbwxzxp41.jpg\" rel=\"nofollow noreferrer noopener\" target=\"_blank\"><img src=\"https://i.redd.it/s9m5xbwxzxp41.jpg\" alt=\"https://i.redd.it/s9m5xbwxzxp41.jpg\" style=\"max-width:100%\"></a><br>\n6 那个假装美籍华人的家伙<br>\n<br>\n<a href=\"https://i.redd.it/ct35fkvxzxp41.jpg\" rel=\"nofollow noreferrer noopener\" target=\"_blank\"><img src=\"https://i.redd.it/ct35fkvxzxp41.jpg\" alt=\"https://i.redd.it/ct35fkvxzxp41.jpg\" style=\"max-width:100%\"></a><br>\n7 不看id的后果<br>\n<br>\n<a href=\"https://i.redd.it/7wou6ntxzxp41.jpg\" rel=\"nofollow noreferrer noopener\" target=\"_blank\"><img src=\"https://i.redd.it/7wou6ntxzxp41.jpg\" alt=\"https://i.redd.it/7wou6ntxzxp41.jpg\" style=\"max-width:100%\"></a><br>\n8 自裁 请<br>\n<br>\n<a href=\"https://i.redd.it/owl1t9vxzxp41.jpg\" rel=\"nofollow noreferrer noopener\" target=\"_blank\"><img src=\"https://i.redd.it/owl1t9vxzxp41.jpg\" alt=\"https://i.redd.it/owl1t9vxzxp41.jpg\" style=\"max-width:100%\"></a><br>\n<a href=\"https://i.redd.it/x9ev24txzxp41.jpg\" rel=\"nofollow noreferrer noopener\" target=\"_blank\"><img src=\"https://i.redd.it/x9ev24txzxp41.jpg\" alt=\"https://i.redd.it/x9ev24txzxp41.jpg\" style=\"max-width:100%\"></a><br>\n9 内外有别<br>\n<br>\n<a href=\"https://i.redd.it/oi25j2uxzxp41.jpg\" rel=\"nofollow noreferrer noopener\" target=\"_blank\"><img src=\"https://i.redd.it/oi25j2uxzxp41.jpg\" alt=\"https://i.redd.it/oi25j2uxzxp41.jpg\" style=\"max-width:100%\"></a><br>\n10 儿子敢和爹提意见？忘了自己姓什么了？穆罕默德 立坚 赵？<br>\n<br>\n<a href=\"https://i.redd.it/y6mz49txzxp41.jpg\" rel=\"nofollow noreferrer noopener\" target=\"_blank\"><img src=\"https://i.redd.it/y6mz49txzxp41.jpg\" alt=\"https://i.redd.it/y6mz49txzxp41.jpg\" style=\"max-width:100%\"></a><br>\n<a href=\"https://i.redd.it/sxinvatxzxp41.jpg\" rel=\"nofollow noreferrer noopener\" target=\"_blank\"><img src=\"https://i.redd.it/sxinvatxzxp41.jpg\" alt=\"https://i.redd.it/sxinvatxzxp41.jpg\" style=\"max-width:100%\"></a><br>\n11 好名字<br>\n<br>\n<a href=\"https://i.redd.it/ot59sqtxzxp41.jpg\" rel=\"nofollow noreferrer noopener\" target=\"_blank\"><img src=\"https://i.redd.it/ot59sqtxzxp41.jpg\" alt=\"https://i.redd.it/ot59sqtxzxp41.jpg\" style=\"max-width:100%\"></a><br>\n12 b站敢死队<br>\n<br>\n<a href=\"https://i.redd.it/bct41tvxzxp41.jpg\" rel=\"nofollow noreferrer noopener\" target=\"_blank\"><img src=\"https://i.redd.it/bct41tvxzxp41.jpg\" alt=\"https://i.redd.it/bct41tvxzxp41.jpg\" style=\"max-width:100%\"></a><br>\n13 一人就是一个n号房<br>\n<br>\n<a href=\"https://i.redd.it/26k12ytxzxp41.jpg\" rel=\"nofollow noreferrer noopener\" target=\"_blank\"><img src=\"https://i.redd.it/26k12ytxzxp41.jpg\" alt=\"https://i.redd.it/26k12ytxzxp41.jpg\" style=\"max-width:100%\"></a><br>\n14 ？？？？？？<br>\n<br>\n<a href=\"https://i.redd.it/w7zi3ltxzxp41.jpg\" rel=\"nofollow noreferrer noopener\" target=\"_blank\"><img src=\"https://i.redd.it/w7zi3ltxzxp41.jpg\" alt=\"https://i.redd.it/w7zi3ltxzxp41.jpg\" style=\"max-width:100%\"></a><br>\n15 历史资料<br>\n<br>\n<a href=\"https://i.redd.it/csiioytxzxp41.jpg\" rel=\"nofollow noreferrer noopener\" target=\"_blank\"><img src=\"https://i.redd.it/csiioytxzxp41.jpg\" alt=\"https://i.redd.it/csiioytxzxp41.jpg\" style=\"max-width:100%\"></a><br>\n<a href=\"https://i.redd.it/0rf9e4uxzxp41.jpg\" rel=\"nofollow noreferrer noopener\" target=\"_blank\"><img src=\"https://i.redd.it/0rf9e4uxzxp41.jpg\" alt=\"https://i.redd.it/0rf9e4uxzxp41.jpg\" style=\"max-width:100%\"></a><br>\n<br>\n<br>\n【翻车新闻】vol 284：电影解说竟敢影射今上！？<br>\n<br>\n1 爽，看你破产吃白饭更爽<br>\n<br>\n<a href=\"https://i.redd.it/4b1focxw0yp41.jpg\" rel=\"nofollow noreferrer noopener\" target=\"_blank\"><img src=\"https://i.redd.it/4b1focxw0yp41.jpg\" alt=\"https://i.redd.it/4b1focxw0yp41.jpg\" style=\"max-width:100%\"></a><br>\n2 有意思。。。<br>\n<br>\n<a href=\"https://i.redd.it/30yz6lxw0yp41.jpg\" rel=\"nofollow noreferrer noopener\" target=\"_blank\"><img src=\"https://i.redd.it/30yz6lxw0yp41.jpg\" alt=\"https://i.redd.it/30yz6lxw0yp41.jpg\" style=\"max-width:100%\"></a><br>\n3 十几万。。。美国”户口\"<br>\n<br>\n<a href=\"https://i.redd.it/i0g2mnxw0yp41.jpg\" rel=\"nofollow noreferrer noopener\" target=\"_blank\"><img src=\"https://i.redd.it/i0g2mnxw0yp41.jpg\" alt=\"https://i.redd.it/i0g2mnxw0yp41.jpg\" style=\"max-width:100%\"></a><br>\n4 那位对线共青团老哥的视频。。。<br>\n<br>\n<a href=\"https://i.redd.it/tjo6fqxw0yp41.jpg\" rel=\"nofollow noreferrer noopener\" target=\"_blank\"><img src=\"https://i.redd.it/tjo6fqxw0yp41.jpg\" alt=\"https://i.redd.it/tjo6fqxw0yp41.jpg\" style=\"max-width:100%\"></a><br>\n<a href=\"https://i.redd.it/ur57txzw0yp41.jpg\" rel=\"nofollow noreferrer noopener\" target=\"_blank\"><img src=\"https://i.redd.it/ur57txzw0yp41.jpg\" alt=\"https://i.redd.it/ur57txzw0yp41.jpg\" style=\"max-width:100%\"></a><br>\n5 居然<mark>支</mark>持辱华品牌！汉奸！<br>\n<br>\n<a href=\"https://i.redd.it/ewcnjgxw0yp41.jpg\" rel=\"nofollow noreferrer noopener\" target=\"_blank\"><img src=\"https://i.redd.it/ewcnjgxw0yp41.jpg\" alt=\"https://i.redd.it/ewcnjgxw0yp41.jpg\" style=\"max-width:100%\"></a><br>\n6 。。。。天啊<br>\n<br>\n<a href=\"https://i.redd.it/nb1cwqxw0yp41.jpg\" rel=\"nofollow noreferrer noopener\" target=\"_blank\"><img src=\"https://i.redd.it/nb1cwqxw0yp41.jpg\" alt=\"https://i.redd.it/nb1cwqxw0yp41.jpg\" style=\"max-width:100%\"></a><br>\n7 知乎奇行种<br>\n<br>\n<a href=\"https://i.redd.it/no7segyw0yp41.jpg\" rel=\"nofollow noreferrer noopener\" target=\"_blank\"><img src=\"https://i.redd.it/no7segyw0yp41.jpg\" alt=\"https://i.redd.it/no7segyw0yp41.jpg\" style=\"max-width:100%\"></a><br>\n8 打倒马云！<br>\n<br>\n<a href=\"https://i.redd.it/kv8u0jyw0yp41.jpg\" rel=\"nofollow noreferrer noopener\" target=\"_blank\"><img src=\"https://i.redd.it/kv8u0jyw0yp41.jpg\" alt=\"https://i.redd.it/kv8u0jyw0yp41.jpg\" style=\"max-width:100%\"></a><br>\n9 你说呢？<br>\n<br>\n<a href=\"https://i.redd.it/ysnoajyw0yp41.jpg\" rel=\"nofollow noreferrer noopener\" target=\"_blank\"><img src=\"https://i.redd.it/ysnoajyw0yp41.jpg\" alt=\"https://i.redd.it/ysnoajyw0yp41.jpg\" style=\"max-width:100%\"></a><br>\n10 那就尴尬了<br>\n<br>\n<a href=\"https://i.redd.it/8hltqiyw0yp41.jpg\" rel=\"nofollow noreferrer noopener\" target=\"_blank\"><img src=\"https://i.redd.it/8hltqiyw0yp41.jpg\" alt=\"https://i.redd.it/8hltqiyw0yp41.jpg\" style=\"max-width:100%\"></a><br>\n11 你敢影射今上？<br>\n<br>\n<a href=\"https://i.redd.it/p5q04kyw0yp41.jpg\" rel=\"nofollow noreferrer noopener\" target=\"_blank\"><img src=\"https://i.redd.it/p5q04kyw0yp41.jpg\" alt=\"https://i.redd.it/p5q04kyw0yp41.jpg\" style=\"max-width:100%\"></a><br>\n<a href=\"https://i.redd.it/ab2lziyw0yp41.jpg\" rel=\"nofollow noreferrer noopener\" target=\"_blank\"><img src=\"https://i.redd.it/ab2lziyw0yp41.jpg\" alt=\"https://i.redd.it/ab2lziyw0yp41.jpg\" style=\"max-width:100%\"></a><br>\n<a href=\"https://i.redd.it/4w1igiyw0yp41.jpg\" rel=\"nofollow noreferrer noopener\" target=\"_blank\"><img src=\"https://i.redd.it/4w1igiyw0yp41.jpg\" alt=\"https://i.redd.it/4w1igiyw0yp41.jpg\" style=\"max-width:100%\"></a><br>\n12 有事找大哥<br>\n<br>\n<a href=\"https://i.redd.it/wf4s0kyw0yp41.jpg\" rel=\"nofollow noreferrer noopener\" target=\"_blank\"><img src=\"https://i.redd.it/wf4s0kyw0yp41.jpg\" alt=\"https://i.redd.it/wf4s0kyw0yp41.jpg\" style=\"max-width:100%\"></a><br>\n13 ？？？？？？？？？？<br>\n<br>\n<a href=\"https://i.redd.it/t1h3tjxw0yp41.jpg\" rel=\"nofollow noreferrer noopener\" target=\"_blank\"><img src=\"https://i.redd.it/t1h3tjxw0yp41.jpg\" alt=\"https://i.redd.it/t1h3tjxw0yp41.jpg\" style=\"max-width:100%\"></a><br>\n14 井底之蛙<br>\n<br>\n<a href=\"https://i.redd.it/c5498jyw0yp41.jpg\" rel=\"nofollow noreferrer noopener\" target=\"_blank\"><img src=\"https://i.redd.it/c5498jyw0yp41.jpg\" alt=\"https://i.redd.it/c5498jyw0yp41.jpg\" style=\"max-width:100%\"></a><br>\n<a href=\"https://i.redd.it/z91lymyw0yp41.jpg\" rel=\"nofollow noreferrer noopener\" target=\"_blank\"><img src=\"https://i.redd.it/z91lymyw0yp41.jpg\" alt=\"https://i.redd.it/z91lymyw0yp41.jpg\" style=\"max-width:100%\"></a><br>\n15 好熟悉啊<br>\n<br>\n<a href=\"https://i.redd.it/0iersx0x0yp41.jpg\" rel=\"nofollow noreferrer noopener\" target=\"_blank\"><img src=\"https://i.redd.it/0iersx0x0yp41.jpg\" alt=\"https://i.redd.it/0iersx0x0yp41.jpg\" style=\"max-width:100%\"></a><br>\n16 谁想复辟啊？<br>\n<br>\n<a href=\"https://i.redd.it/04mflfxw0yp41.jpg\" rel=\"nofollow noreferrer noopener\" target=\"_blank\"><img src=\"https://i.redd.it/04mflfxw0yp41.jpg\" alt=\"https://i.redd.it/04mflfxw0yp41.jpg\" style=\"max-width:100%\"></a><br>\n<br>\n<br>\n<br>\n<i>本次新闻播放完毕，谢谢欣赏！再次感谢原OP s1refugee的汇总！</i><br>\n<br>\n<blockquote>翻车新闻膜乎搬运版由@有事找大哥、@匿名用户、@Artemis、@富平衣逼、@Caritas、@Christina、@掀翻小池塘、@恶习像弹簧、<s>@通音宽依</s>、@匿名用尸等网友搬运。若您想订阅翻车新闻膜乎搬运版，请关注标签“【翻车新闻】”获得更新。</blockquote><br>\n<br>\n下一篇：<a href=\"https://mohu.rocks/article/1727\">https://mohu.rocks/article/1727</a><br>\n上一篇：<a href=\"https://mohu.rocks/article/1992\">https://mohu.rocks/article/1992</a><br>\n<br>\n<br>\n<b>投稿地址：</b><br>\n<a href=\"https://www.reddit.com/r/hanren\" rel=\"nofollow noreferrer noopener\" target=\"_blank\">https://www.reddit.com/r/hanren</a><br>\n<br>\n<b>往期链接：</b><br>\n&gt;Reddit原版<br>\n<a href=\"https://www.reddit.com/user/s1refugee/posts/\" rel=\"nofollow noreferrer noopener\" target=\"_blank\">https://www.reddit.com/user/s1refugee/posts/</a><br>\n<br>\n&gt;膜乎搬运版<br>\n<a href=\"https://mohu.rocks/topic/【翻车新闻】\">https://mohu.rocks/topic/【翻车新闻】</a><br>\n<br>\n&gt;新品葱搬运版<br>\n<a href=\"https://pincong.rocks/topic/翻车新闻\" rel=\"nofollow noreferrer noopener\" target=\"_blank\">https://pincong.rocks/topic/翻车新闻</a><br>\n<br>\n&gt;@<a href=\"https://pincong.rocks/people/ikuyui\" rel=\"nofollow noreferrer noopener\" target=\"_blank\">ikuyui</a> telegram版<br>\n<a href=\"https://t.me/s/pincongonline\" rel=\"nofollow noreferrer noopener\" target=\"_blank\">https://t.me/s/pincongonline</a><br>\n<br>\n&gt;@疯狂文宣掀翻小品葱 <br>\n<a href=\"https://t.me/awuyiudhaegiudiaj\" rel=\"nofollow noreferrer noopener\" target=\"_blank\">https://t.me/awuyiudhaegiudiaj</a><br>\n<br>\n<i>Be the first to share what you think!</i>","date":"2020-05-10","agreeCount":0,"discussionCount":0}