{"type":"article","id":3773,"title":"【翻车新闻】594 最近不少阿q被赵弹了","uid":7510,"topics":[584,4384],"contents":"搬运自Reddit群组<a href=\"https://www.reddit.com/r/hanren\" rel=\"nofollow noreferrer noopener\" target=\"_blank\">r/hanren</a>，由<a href=\"https://www.reddit.com/user/s1refugee\" rel=\"nofollow noreferrer noopener\" target=\"_blank\">u/s1refugee</a>整理。<br>\n原地址：<a href=\"https://www.reddit.com/r/hanren/comments/j8xt9p\" rel=\"nofollow noreferrer noopener\" target=\"_blank\">【翻车新闻】594：最近不少阿q被赵弹了</a><br>\n<br>\n<br>\n<br>\n1  政治觉悟很高啊<br>\n<br>\n<a href=\"https://i.redd.it/3iwajk9grds51.jpg\" rel=\"nofollow noreferrer noopener\" target=\"_blank\"><img src=\"https://i.redd.it/3iwajk9grds51.jpg\" alt=\"https://i.redd.it/3iwajk9grds51.jpg\" style=\"max-width:100%\"></a><br>\n<br>\n2 这是真的还是假的？<br>\n<br>\n<a href=\"https://i.redd.it/gvap4nagrds51.jpg\" rel=\"nofollow noreferrer noopener\" target=\"_blank\"><img src=\"https://i.redd.it/gvap4nagrds51.jpg\" alt=\"https://i.redd.it/gvap4nagrds51.jpg\" style=\"max-width:100%\"></a><br>\n<br>\n<a href=\"https://i.redd.it/jsb4lycgrds51.jpg\" rel=\"nofollow noreferrer noopener\" target=\"_blank\"><img src=\"https://i.redd.it/jsb4lycgrds51.jpg\" alt=\"https://i.redd.it/jsb4lycgrds51.jpg\" style=\"max-width:100%\"></a><br>\n<br>\n3 不是很久以前的旧闻了吗？为什么现在才爆出来？<br>\n<br>\n<a href=\"https://i.redd.it/if0wzzcgrds51.jpg\" rel=\"nofollow noreferrer noopener\" target=\"_blank\"><img src=\"https://i.redd.it/if0wzzcgrds51.jpg\" alt=\"https://i.redd.it/if0wzzcgrds51.jpg\" style=\"max-width:100%\"></a><br>\n<br>\n4 花呗你做个人吧<br>\n<br>\n<a href=\"https://i.redd.it/p693aq9grds51.jpg\" rel=\"nofollow noreferrer noopener\" target=\"_blank\"><img src=\"https://i.redd.it/p693aq9grds51.jpg\" alt=\"https://i.redd.it/p693aq9grds51.jpg\" style=\"max-width:100%\"></a><br>\n<br>\n5 知乎老阴阳人<br>\n<br>\n<a href=\"https://i.redd.it/oxct8l9grds51.jpg\" rel=\"nofollow noreferrer noopener\" target=\"_blank\"><img src=\"https://i.redd.it/oxct8l9grds51.jpg\" alt=\"https://i.redd.it/oxct8l9grds51.jpg\" style=\"max-width:100%\"></a><br>\n<br>\n6 不能让友邦惊诧！<br>\n<br>\n<a href=\"https://i.redd.it/aef4mjagrds51.jpg\" rel=\"nofollow noreferrer noopener\" target=\"_blank\"><img src=\"https://i.redd.it/aef4mjagrds51.jpg\" alt=\"https://i.redd.it/aef4mjagrds51.jpg\" style=\"max-width:100%\"></a><br>\n<br>\n<a href=\"https://i.redd.it/fq1gosagrds51.jpg\" rel=\"nofollow noreferrer noopener\" target=\"_blank\"><img src=\"https://i.redd.it/fq1gosagrds51.jpg\" alt=\"https://i.redd.it/fq1gosagrds51.jpg\" style=\"max-width:100%\"></a><br>\n<br>\n7 你也配姓赵？真敢议论赵家人？<br>\n<br>\n<a href=\"https://i.redd.it/rzu21oagrds51.jpg\" rel=\"nofollow noreferrer noopener\" target=\"_blank\"><img src=\"https://i.redd.it/rzu21oagrds51.jpg\" alt=\"https://i.redd.it/rzu21oagrds51.jpg\" style=\"max-width:100%\"></a><br>\n<br>\n<a href=\"https://i.redd.it/cwq9c0dgrds51.jpg\" rel=\"nofollow noreferrer noopener\" target=\"_blank\"><img src=\"https://i.redd.it/cwq9c0dgrds51.jpg\" alt=\"https://i.redd.it/cwq9c0dgrds51.jpg\" style=\"max-width:100%\"></a><br>\n<br>\n8 哇 这个是直接被撸掉了编制啊<br>\n<br>\n<a href=\"https://i.redd.it/5xkyblagrds51.jpg\" rel=\"nofollow noreferrer noopener\" target=\"_blank\"><img src=\"https://i.redd.it/5xkyblagrds51.jpg\" alt=\"https://i.redd.it/5xkyblagrds51.jpg\" style=\"max-width:100%\"></a><br>\n<br>\n9 网易怎么也整改了？<br>\n<br>\n<a href=\"https://i.redd.it/qq62ju9grds51.jpg\" rel=\"nofollow noreferrer noopener\" target=\"_blank\"><img src=\"https://i.redd.it/qq62ju9grds51.jpg\" alt=\"https://i.redd.it/qq62ju9grds51.jpg\" style=\"max-width:100%\"></a><br>\n<br>\n<a href=\"https://i.redd.it/5ztpllagrds51.jpg\" rel=\"nofollow noreferrer noopener\" target=\"_blank\"><img src=\"https://i.redd.it/5ztpllagrds51.jpg\" alt=\"https://i.redd.it/5ztpllagrds51.jpg\" style=\"max-width:100%\"></a><br>\n<br>\n10 合法翻墙的那个游览器已经被干烂了<br>\n<br>\n<a href=\"https://i.redd.it/946p8l9grds51.jpg\" rel=\"nofollow noreferrer noopener\" target=\"_blank\"><img src=\"https://i.redd.it/946p8l9grds51.jpg\" alt=\"https://i.redd.it/946p8l9grds51.jpg\" style=\"max-width:100%\"></a><br>\n<br>\n<a href=\"https://i.redd.it/jhxjbm9grds51.jpg\" rel=\"nofollow noreferrer noopener\" target=\"_blank\"><img src=\"https://i.redd.it/jhxjbm9grds51.jpg\" alt=\"https://i.redd.it/jhxjbm9grds51.jpg\" style=\"max-width:100%\"></a><br>\n<br>\n12 别吓唬人。。。<br>\n<br>\n<a href=\"https://i.redd.it/4m4koragrds51.jpg\" rel=\"nofollow noreferrer noopener\" target=\"_blank\"><img src=\"https://i.redd.it/4m4koragrds51.jpg\" alt=\"https://i.redd.it/4m4koragrds51.jpg\" style=\"max-width:100%\"></a><br>\n<br>\n13 ？？？？？<br>\n<br>\n<a href=\"https://i.redd.it/z0u6pycgrds51.jpg\" rel=\"nofollow noreferrer noopener\" target=\"_blank\"><img src=\"https://i.redd.it/z0u6pycgrds51.jpg\" alt=\"https://i.redd.it/z0u6pycgrds51.jpg\" style=\"max-width:100%\"></a><br>\n<br>\n14  又一个赴美是生活的？<br>\n<br>\n<a href=\"https://i.redd.it/ideghpagrds51.jpg\" rel=\"nofollow noreferrer noopener\" target=\"_blank\"><img src=\"https://i.redd.it/ideghpagrds51.jpg\" alt=\"https://i.redd.it/ideghpagrds51.jpg\" style=\"max-width:100%\"></a><br>\n<br>\n15 连回车都不会用的赛博大师<br>\n<br>\n<a href=\"https://i.redd.it/lbfhll9grds51.jpg\" rel=\"nofollow noreferrer noopener\" target=\"_blank\"><img src=\"https://i.redd.it/lbfhll9grds51.jpg\" alt=\"https://i.redd.it/lbfhll9grds51.jpg\" style=\"max-width:100%\"></a><br>\n<br>\n16 这是要加速还是减速？<br>\n<br>\n<a href=\"https://i.redd.it/5nalal9grds51.jpg\" rel=\"nofollow noreferrer noopener\" target=\"_blank\"><img src=\"https://i.redd.it/5nalal9grds51.jpg\" alt=\"https://i.redd.it/5nalal9grds51.jpg\" style=\"max-width:100%\"></a><br>\n<br>\n<br>\n<br>\n<b>上一期：<a href=\"https://mohu.rocks/article/3765\">https://mohu.rocks/article/3765</a></b><br>\n<b>下一期：<a href=\"https://mohu.rocks/article/3809\">https://mohu.rocks/article/3809</a></b><br>\n<br>\n再次感谢s1refugee的整理工作。<br>\n<blockquote>翻车新闻膜乎搬运版由@有事找大哥、@匿名用户、@Artemis、@富平衣逼、@Caritas、@Christina、@掀翻小池塘、@恶习像弹簧、@匿名用尸、@白咲花等网友搬运。若您想订阅翻车新闻膜乎搬运版，请关注标签“【翻车新闻】”获得更新。</blockquote><br>\n<br>\n<b>投稿地址：</b><br>\n<a href=\"https://www.reddit.com/r/hanren\" rel=\"nofollow noreferrer noopener\" target=\"_blank\">https://www.reddit.com/r/hanren</a><br>\n<br>\n<b>往期链接：</b><br>\n&gt;Reddit原版<br>\n<a href=\"https://www.reddit.com/user/s1refugee/posts\" rel=\"nofollow noreferrer noopener\" target=\"_blank\">https://www.reddit.com/user/s1refugee/posts</a><br>\n<br>\n&gt;膜乎搬运版<br>\n<a href=\"https://mohu.rocks/topic/【翻车新闻】\">https://mohu.rocks/topic/【翻车新闻】</a><br>\n<br>\n&gt;新品葱搬运版<br>\n<a href=\"https://pincong.rocks/topic/翻车新闻\" rel=\"nofollow noreferrer noopener\" target=\"_blank\">https://pincong.rocks/topic/翻车新闻</a><br>\n<br>\n&gt;@<a href=\"https://pincong.rocks/people/ikuyui\" rel=\"nofollow noreferrer noopener\" target=\"_blank\">ikuyui</a> telegram版<br>\n<a href=\"https://t.me/s/pincongonline\" rel=\"nofollow noreferrer noopener\" target=\"_blank\">https://t.me/s/pincongonline</a><br>\n<br>\n&gt;@疯狂文宣掀翻小品葱<br>\n<a href=\"https://t.me/s/awuyiudhaegiudiaj\" rel=\"nofollow noreferrer noopener\" target=\"_blank\">https://t.me/s/awuyiudhaegiudiaj</a><br>\n<br>\n<i>Be the first to share what you think!</i>","date":"2020-10-12","agreeCount":2,"discussionCount":0}