{"type":"article","id":3906,"title":"搏击俱乐部的“奇葩说话方式”本质上是职场上“老资历”对“菜鸟”的调弄","uid":6760,"topics":[1454,1725,3243],"contents":"<a href=\"https://2047.name/t/8338#104052\" rel=\"nofollow noreferrer noopener\" target=\"_blank\">https://2047.name/t/8338#104052</a><br>\n<br>\n<blockquote>我觉得与其说是sugar coating，不如说是典型的办公室gossip文化。聚在一起或者背后说人坏话，但是说得又不能太直接，否则容易被人抓住破绽；所以一定要拐弯抹角，半含半露，欲言又止，似是而非，在满足自己的gossip需求时留有免责余地；如果别人反驳还可以带着蔑视的神色来一句，我又没说你，你自己想太多。<br>\n<br>\n比如我想骂品葱，可以直接说：品葱高管乱捉鬼，搞逆向淘汰，真是一帮蠢材！<br>\n<br>\n也可以学着鹿儿说话：墙外舆论引导不易，感谢品葱的正义人士承担这个艰巨的任务。<br>\n<br>\n也可以学着斯基说话：新葱诸君若是以为靠建立一层充满反智主义的妖塔便可建立墙外舆论边界，实属一厢情愿。<br>\n<br>\n或者学着站长说话： 品韭 的一帮牛鬼蛇神演得累不累啊？<br>\n<br>\n这种话不是不会说，只是真是没意思。<br>\n</blockquote><br>\n<br>\n我觉得这段话说得非常有力，简直是一针见血。搏击俱乐部如此toXIc的氛围背后其实也就那么回事：一群办公室老资历在那调弄“菜鸟”，一边调弄一边互相说着只有老资历懂的语言还一边“嘿嘿嘿”在那傻笑，菜鸟不明所以也觉得奇怪，问又问不出个所以然；脾气不好的估计当场就要爆炸了，然后老资历又开始互相讽刺说“这菜鸟太逊了，这么快就火了，我们还没怎么样呢”。","date":"2020-10-23","agreeCount":3,"discussionCount":0}