{"type":"article","id":4321,"title":"【翻车新闻】664 终于猫和老鼠也辱华了！ 🐸","uid":7510,"topics":[584],"contents":"搬运自Reddit群组<a href=\"https://www.reddit.com/r/hanren\" rel=\"nofollow noreferrer noopener\" target=\"_blank\">r/hanren</a>，由<a href=\"https://www.reddit.com/user/s1refugee\" rel=\"nofollow noreferrer noopener\" target=\"_blank\">u/s1refugee</a>整理。<br>\n原地址：<a href=\"https://www.reddit.com/r/hanren/comments/k2ft1x\" rel=\"nofollow noreferrer noopener\" target=\"_blank\">【翻车新闻】664 终于猫和老鼠也辱华了！</a><br>\n<br>\n<br>\n1 好，先从你开始！<br>\n<br>\n<a href=\"https://i.redd.it/5e3khazl8w161.jpg\" rel=\"nofollow noreferrer noopener\" target=\"_blank\"><img src=\"https://i.redd.it/5e3khazl8w161.jpg\" alt=\"https://i.redd.it/5e3khazl8w161.jpg\" style=\"max-width:100%\"></a><br>\n<br>\n2 据说之前家暴死的那个也被阴婚了？<br>\n<br>\n<a href=\"https://i.redd.it/m0og3lzl8w161.jpg\" rel=\"nofollow noreferrer noopener\" target=\"_blank\"><img src=\"https://i.redd.it/m0og3lzl8w161.jpg\" alt=\"https://i.redd.it/m0og3lzl8w161.jpg\" style=\"max-width:100%\"></a><br>\n<br>\n3 全都是美帝的错！<br>\n<br>\n<a href=\"https://i.redd.it/r8yc28zl8w161.jpg\" rel=\"nofollow noreferrer noopener\" target=\"_blank\"><img src=\"https://i.redd.it/r8yc28zl8w161.jpg\" alt=\"https://i.redd.it/r8yc28zl8w161.jpg\" style=\"max-width:100%\"></a><br>\n<br>\n<a href=\"https://i.redd.it/s7c43mzl8w161.jpg\" rel=\"nofollow noreferrer noopener\" target=\"_blank\"><img src=\"https://i.redd.it/s7c43mzl8w161.jpg\" alt=\"https://i.redd.it/s7c43mzl8w161.jpg\" style=\"max-width:100%\"></a><br>\n<br>\n4 毛路线？你这是看不起主体思想！<br>\n<br>\n<a href=\"https://i.redd.it/5ev41kzl8w161.jpg\" rel=\"nofollow noreferrer noopener\" target=\"_blank\"><img src=\"https://i.redd.it/5ev41kzl8w161.jpg\" alt=\"https://i.redd.it/5ev41kzl8w161.jpg\" style=\"max-width:100%\"></a><br>\n<br>\n5 终于猫和老鼠也辱华了！<br>\n<br>\n<a href=\"https://i.redd.it/t7n6mg2m8w161.jpg\" rel=\"nofollow noreferrer noopener\" target=\"_blank\"><img src=\"https://i.redd.it/t7n6mg2m8w161.jpg\" alt=\"https://i.redd.it/t7n6mg2m8w161.jpg\" style=\"max-width:100%\"></a><br>\n<br>\n6 最后果不其然是受害者道歉<br>\n<br>\n<a href=\"https://i.redd.it/x2j9orzl8w161.jpg\" rel=\"nofollow noreferrer noopener\" target=\"_blank\"><img src=\"https://i.redd.it/x2j9orzl8w161.jpg\" alt=\"https://i.redd.it/x2j9orzl8w161.jpg\" style=\"max-width:100%\"></a><br>\n<br>\n7 万万没想到啊<br>\n<br>\n<a href=\"https://i.redd.it/se2fvrzl8w161.jpg\" rel=\"nofollow noreferrer noopener\" target=\"_blank\"><img src=\"https://i.redd.it/se2fvrzl8w161.jpg\" alt=\"https://i.redd.it/se2fvrzl8w161.jpg\" style=\"max-width:100%\"></a><br>\n<br>\n8 谁说大大没行动的？<br>\n<br>\n<a href=\"https://i.redd.it/j43as8zl8w161.jpg\" rel=\"nofollow noreferrer noopener\" target=\"_blank\"><img src=\"https://i.redd.it/j43as8zl8w161.jpg\" alt=\"https://i.redd.it/j43as8zl8w161.jpg\" style=\"max-width:100%\"></a><br>\n<br>\n9 能在表演一下那个吗？<br>\n<br>\nb站只会倒闭，不会变质<br>\n<br>\n哈哈哈哈哈<br>\n<br>\n<a href=\"https://i.redd.it/1pdyqnzl8w161.jpg\" rel=\"nofollow noreferrer noopener\" target=\"_blank\"><img src=\"https://i.redd.it/1pdyqnzl8w161.jpg\" alt=\"https://i.redd.it/1pdyqnzl8w161.jpg\" style=\"max-width:100%\"></a><br>\n<br>\n<a href=\"https://i.redd.it/fqfx3szl8w161.jpg\" rel=\"nofollow noreferrer noopener\" target=\"_blank\"><img src=\"https://i.redd.it/fqfx3szl8w161.jpg\" alt=\"https://i.redd.it/fqfx3szl8w161.jpg\" style=\"max-width:100%\"></a><br>\n<br>\n10 b站敢死队<br>\n<br>\n<a href=\"https://i.redd.it/ambd3nzl8w161.jpg\" rel=\"nofollow noreferrer noopener\" target=\"_blank\"><img src=\"https://i.redd.it/ambd3nzl8w161.jpg\" alt=\"https://i.redd.it/ambd3nzl8w161.jpg\" style=\"max-width:100%\"></a><br>\n<br>\n11 新财富密码啊<br>\n<br>\n<a href=\"https://i.redd.it/dvk83nzl8w161.jpg\" rel=\"nofollow noreferrer noopener\" target=\"_blank\"><img src=\"https://i.redd.it/dvk83nzl8w161.jpg\" alt=\"https://i.redd.it/dvk83nzl8w161.jpg\" style=\"max-width:100%\"></a><br>\n<br>\n12 你也配和大大一个姓？<br>\n<br>\n<a href=\"https://i.redd.it/rizoj8zl8w161.jpg\" rel=\"nofollow noreferrer noopener\" target=\"_blank\"><img src=\"https://i.redd.it/rizoj8zl8w161.jpg\" alt=\"https://i.redd.it/rizoj8zl8w161.jpg\" style=\"max-width:100%\"></a><br>\n<br>\n13 不好的预感<br>\n<br>\n<a href=\"https://i.redd.it/fotlf61m8w161.jpg\" rel=\"nofollow noreferrer noopener\" target=\"_blank\"><img src=\"https://i.redd.it/fotlf61m8w161.jpg\" alt=\"https://i.redd.it/fotlf61m8w161.jpg\" style=\"max-width:100%\"></a><br>\n<br>\n14 一步到位多好啊<br>\n<br>\n<a href=\"https://i.redd.it/o7nowkzl8w161.jpg\" rel=\"nofollow noreferrer noopener\" target=\"_blank\"><img src=\"https://i.redd.it/o7nowkzl8w161.jpg\" alt=\"https://i.redd.it/o7nowkzl8w161.jpg\" style=\"max-width:100%\"></a><br>\n<br>\n<a href=\"https://i.redd.it/21h62zzl8w161.jpg\" rel=\"nofollow noreferrer noopener\" target=\"_blank\"><img src=\"https://i.redd.it/21h62zzl8w161.jpg\" alt=\"https://i.redd.it/21h62zzl8w161.jpg\" style=\"max-width:100%\"></a><br>\n<br>\n15 自己打自己脸<br>\n<br>\n<a href=\"https://i.redd.it/djfstt0m8w161.jpg\" rel=\"nofollow noreferrer noopener\" target=\"_blank\"><img src=\"https://i.redd.it/djfstt0m8w161.jpg\" alt=\"https://i.redd.it/djfstt0m8w161.jpg\" style=\"max-width:100%\"></a><br>\n<br>\n<a href=\"https://i.redd.it/ve1gk01m8w161.jpg\" rel=\"nofollow noreferrer noopener\" target=\"_blank\"><img src=\"https://i.redd.it/ve1gk01m8w161.jpg\" alt=\"https://i.redd.it/ve1gk01m8w161.jpg\" style=\"max-width:100%\"></a><br>\n<br>\n<br>\n<b>上一期：<a href=\"https://mohu.rocks/article/4320\">https://mohu.rocks/article/4320</a></b><br>\n<b>下一期：还没钦定。</b>","date":"2020-11-29","agreeCount":2,"discussionCount":0}