{"type":"answer","id":59871,"parentType":"question","parentId":13885,"uid":6760,"contents":"一直都是这样的啊。<br>\n姨学氛围早期更浓，五毛粉红早期更多（因为当时小二是允许五毛粉红进入品葱的，只要不骂脏话、好好讨论就行），现在看起来比较疯的管理员（如killredragon）甚至比起早期已经保持了最大限度的克制。<br>\n建站没多久香港抗争发生，第一次人口大涌入，然后中共病毒，第二次大涌入，然后就是美国大选，讨论激烈地要死。每一次人口涌入都会带入一堆“低质量”用户，紧跟着就是抓鬼抓网军、筛新人。这么多破事，还不算上早期和中期激烈无比的权术大战、习惯法大战和各种闹剧。<br>\n本来就没一天清净的。<br>\n一般大家回看过去时都会自动忽略掉坏的回忆，只记得当时好像多么多么好，这样那样的，这又“黄金时代”那又怎么着的，其实只是因为好的东西浮上来了，而烂的东西沉底了而已。不信你去水区，或者甚至不需要是水区，翻到几十页后，就大概能明白了。每个时期都有好的帖，而每个时期都有坏的，享受就好。","date":"2021-01-01","agreeCount":2,"discussionCount":0}