{"type":"answer","id":20781,"parentType":"question","parentId":4948,"uid":3217,"contents":"首先，这种大脑降级还献祭亲妈的自干五你鸟它干嘛？屏蔽就完事了，让他对着镜子打靶，好让众人看畜牲的笑话。<br>\n<br>\n其次，我再来反驳这种迫真又脑残的言论<br>\n1.你确定十年后就是另外一个领导人而不是习近平？还是你在变相暗示包子活不过十年？<br>\n<br>\n2.学习或崇拜一个人都是取其精华，去其糟粕。我膜蛤是膜长者的优良素养，他的精神内涵，学习他的人生经验、开明思想与渊博的学识。<br>\n<br>\n3.反观包子，它有什么可膜的？前者蛤蟆原是乳名因其人贤民博学而人人膜之，后者大大原是膜名因其人昏庸无能而人人乳之。<br>\n它唯一可膜的就是搞乱了这个党，搞垮了这个党，把中共这辆黑车倒着往阴沟里开。不然我膜他干什么？<br>\n膜它力能扛麦盖世兮？膜它日游千米不懈兮？膜它博古通今，知晓中西，满嘴书名，通假字不离口兮？这有什么好膜的，脑子被活摘了才去膜包。<br>\n<br>\n4.再者有多少官员权贵，社会精英拼了命在把自己的家人和个人资产往国外送，你这个韭菜知道吗？这个国家都他妈快完蛋了你还翻墙出来舔你刁野爹屁眼。<br>\n你就应该正大光明的把手机/电脑翻墙爱国的事情全部交给网警，再让他们来告诉你有多爱国！","date":"2019-07-01","agreeCount":18,"discussionCount":2}