{"type":"article_comment","id":34608,"parentType":"article","parentId":1074,"uid":4423,"contents":"<blockquote>说点和膜乎无关的话：加速主义在中国可不可行，我不能给一个肯定的回答，只能说风险特别大（因为中国拥核）...</blockquote><br>\n在我看来，加速主义是可行的。<br>\n必须承认的是，与前苏联的现实主义相比，中共在思维模式的确有很多不同，这也是前苏联为什么几次在紧要关头有能力发动核打击却没有这么做的原因。也有人因此就认为，中共它比苏联更加疯狂。<br>\n我不同意这种观点。在我看来，只要了解中共这个体制，就应该认识到，这个体制在许多方面的可预测性并不比苏共弱，而且也更为理性。但是与苏共相比，中共的理性，是短期的。也就是说，你必须让他能够意识到自己做的事情会招来立即的、迅速、精准的报复。就训练像一条狗一样，你必须每教会它一个动作，就立即给他喂食。中共体制内部充满的都是精致而又短视的利己主义者。他们看起来疯狂是因为他们不认为自己的行为会立刻反馈到自己的身上，但是只要有一种及时的反馈，哪怕力道极低，就可以引起他们巨大的恐惧。这也就能解释为什么当美国禁止共产党员入境时，退党的搜索强度上升了一千倍。<br>\n因此，各国政府对付中共的办法就是给予他们即刻而又精准的反击。而加速主义就是在催促他们采取行动。举个例子，西方政府可以有针对性地对中共的一些官员的子女展开司法调查。比如调查他们的生活费是怎么来的、电脑里有没有恋童视频等等。这些都是在法律允许的范围内，而且即使只是摆出一副要开始的姿态，就足以强迫许多中共的官员进行妥协。","date":"2021-02-09","agreeCount":1,"discussionCount":0}