{"type":"article_comment","id":34684,"parentType":"article","parentId":1074,"uid":4423,"contents":"<blockquote>我不赞同这个观点，因为民主化的进程不仅需要外部的施压，更需要内部的努力和制约，以及监督和批评，否则仍...</blockquote><br>\n你的这种希望，有一定的可能性会成真。但是也有一种可能性是不会成真。中国目前的一个巨大的问题是国内没有一个有全国性威望的反对派领袖或者反对派组织。国外的民主运动，不管是哪个国家，在民主化过程正式开启之前，很多都会有一个领袖或者组织。比如缅甸有昂山素季，苏联有叶利钦和戈尔巴乔夫，南非有曼德拉，美国有华盛顿，香港有黄之峰等等。即使没有领袖，也可以有组织，比如波兰的团结工会。所以中国的未来，很有可能是崩解而不是整体的转型，并且会分裂成不同的政治实体。更坏的结果是像各个王朝末年一样，形成不同的割据政权。当然，这是民主化必须要经历的过程。就像法国大革命一样，国王不下台，不经历几十年的血雨腥风，法国永远也无法民主。","date":"2021-02-11","agreeCount":1,"discussionCount":0}