{"type":"article_comment","id":19226,"parentType":"article","parentId":2444,"uid":6760,"contents":"天使送外卖<br>\n天使送外卖：给你看大脑斧，可凶可凶了呢 ¡评论配图<br>\n<br>\n回复<br>\n赞3<br>\n7月22日 17:15<br>\n行者舞姜<br>\n行者舞姜：虽然气温不是特别高，但空气质量却依然不好，为什么只有西北风时候才能好些呢？<br>\n回复<br>\n赞1<br>\n7月22日 17:14<br>\n味满足<br>\n味满足：老哥，没事，就来看看<br>\n回复<br>\n赞1<br>\n7月22日 17:13<br>\n涵泳飞白<br>\n涵泳飞白：想的通，只是shil和chouch无法控制……<br>\n回复<br>\n赞2<br>\n7月22日 17:04<br>\n乒乒乓乓乒球<br>\n乒乒乓乓乒球：猪有记忆吗，可能没有<br>\n回复<br>\n赞2<br>\n7月22日 17:03<br>\n要不要去散步d<br>\n要不要去散步d：工作要做一个抗击疫情的ppt，想到来这看下。泪奔[泪]<br>\n回复<br>\n赞3<br>\n7月22日 17:02<br>\n飏飏乾<br>\n飏飏乾：好久不见李医生，今天是我和他认识一周年，早在很久就想在今天和他说点什么，可是真的到了这天却什么也说不出来 ，可能只有我记得这个微小的日子<br>\n回复<br>\n赞3<br>\n7月22日 17:01<br>\n假如我真的智障<br>\n假如我真的智障：我一直就是一个害怕死亡的人，也极为功利，慢慢的我开始敬佩很多人，这些人在我的生活中不断地散发出光和热<br>\n回复<br>\n赞3<br>\n7月22日 17:00<br>\n无饭氏<br>\n无饭氏：李叔好，明天我就成年啦！<br>\n回复<br>\n赞5<br>\n7月22日 16:53<br>\nYuniHaaaa<br>\nYuniHaaaa：李医生，我之前把我今年找女朋友的运气都给您了，今天高考分数要出来了，可以的话，帮帮忙呗[泪]<br>\n回复<br>\n赞5<br>\n7月22日 16:51<br>\n红琴海WJH<br>\n红琴海WJH：有段时间没来了，你的二宝一定很可爱<br>\n回复<br>\n赞3<br>\n7月22日 16:46<br>\n粑粑里扣金针菇<br>\n粑粑里扣金针菇：烦透了<br>\n回复<br>\n赞1<br>\n7月22日 16:43<br>\n晶晶krystal1212<br>\n晶晶krystal1212：人一遇见爱情就会失去理智吧<br>\n回复<br>\n赞2<br>\n7月22日 16:42<br>\n随缘_清净心<br>\n随缘_清净心：烂透了<br>\n回复<br>\n赞2<br>\n7月22日 16:40<br>\n影子花雕 等人 共1条回复<br>\n随缘_清净心<br>\n随缘_清净心：李现代言了伊利，什么钱都赚？多喝三聚氰胺<br>\n回复<br>\n赞3<br>\n7月22日 16:38<br>\n种螃蟹的小猴<br>\n种螃蟹的小猴：[蜡烛]<br>\n回复<br>\n赞1<br>\n7月22日 16:38<br>\n种螃蟹的小猴<br>\n种螃蟹的小猴：🙏<br>\n回复<br>\n赞1<br>\n7月22日 16:38<br>\n徐小阳网上冲浪<br>\n徐小阳网上冲浪：李医生…我好想…去看看你…我恨我自己连离开也做不到洒脱…如果能熬过这一年…我就晚点再去看你吧……<br>\n回复<br>\n赞2<br>\n7月22日 16:36<br>\n一叶知秋yeyeye 等人 共2条回复<br>\n谦子杜<br>\n谦子杜：谢谢您<br>\n回复<br>\n赞<br>\n7月22日 16:34<br>\n解放碑的老重庆<br>\n解放碑的老重庆：李医生天气好热，洪水也大！<br>\n回复<br>\n赞<br>\n7月22日 16:33<br>\n网瘾少年陈日天<br>\n网瘾少年陈日天：别吵，你可以听得到。 稳住心跳，用力微笑。 害怕，就拼命奔跑。 那个出口，就快找到。<br>\n回复<br>\n赞1<br>\n7月22日 16:29<br>\nMilkility<br>\nMilkility：李医生，常来看看你，就不会忘记这个冬天<br>\n回复<br>\n赞1<br>\n7月22日 16:28<br>\nEuwerlyr<br>\nEuwerlyr：来看看你<br>\n回复<br>\n赞1<br>\n7月22日 16:26<br>\n2ubfjxa<br>\n2ubfjxa：今天下了好大的雨。<br>\n回复<br>\n赞<br>\n7月22日 16:24<br>\n墨染Seanfly<br>\n墨染Seanfly：下午好，李医生<br>\n回复<br>\n赞<br>\n7月22日 16:24<br>\n搬离之后<br>\n搬离之后：李医生 外公帮我捡了一只乌龟 我想好好养它 可是我有点害怕自己没那个能力 我想起了以前养的小兔子 有一天下暴雨但是我在学校 小兔子就被淋死了[失望]是我没照顾好他 我现在想起来突然就觉得好难过 我总觉得我没能力照顾好这些来到我家的小生灵[失望]李医生 帮我告诉那只小兔子噢 我很想他[泪]<br>\n回复<br>\n赞7<br>\n7月22日 16:02<br>\n柳觞儿<br>\n柳觞儿：医生说进一步检查一下，和家人一起来吧。我就不想去了，不是怕，就突然心踏实了。今天下雨了，七月的夏天没有太阳，雨水弄脏了白鞋。灰天黑地的，李医生，今年的夏天可真不像话。<br>\n回复<br>\n赞7<br>\n7月22日 16:01<br>\n酸菜鱼今天也很丧<br>\n酸菜鱼今天也很丧：今天我和妈妈拿到了爸爸的尸检报告，这是比他的离世更让我们无法接受的事情。<br>\n回复<br>\n赞1<br>\n7月22日 15:59<br>\n-一只张张鸭-<br>\n-一只张张鸭-：李医生希望您在那边永远开心<br>\n回复<br>\n赞<br>\n7月22日 15:54<br>\n_hfc成_<br>\n_hfc成_：亮子，也无风雨也无晴<br>\n回复<br>\n赞1<br>\n7月22日 15:54<br>\n一位普通用户xjl<br>\n一位普通用户xjl：今天大暑，北京挺闷的。您还好吗<br>\n回复<br>\n赞<br>\n7月22日 15:53<br>\n是你小时候的样子<br>\n是你小时候的样子：李医生雨下的好大啊<br>\n回复<br>\n赞<br>\n7月22日 15:53<br>\n希望小熊要开心<br>\n希望小熊要开心：李医生下午好！最近过的蛮开心的 希望你也开心<br>\n回复<br>\n赞<br>\n7月22日 15:52<br>\n聲妹儿的架子鼓<br>\n聲妹儿的架子鼓：李医生 浙大学生qj却只是留校察看 李医生 这社会怎么这么黑暗啊<br>\n回复<br>\n赞1<br>\n7月22日 15:52<br>\n英国前沿 等人 共2条回复<br>\n亲斤氵良Blog抄袭了什么<br>\n亲斤氵良Blog抄袭了什么：【一个健康的社会不应该只有一种声音】<br>\n回复<br>\n赞9<br>\n7月22日 15:49<br>\n大力水手1969081921<br>\n大力水手1969081921：又下雨了<br>\n回复<br>\n赞<br>\n7月22日 15:46<br>\n护士黄菊<br>\n护士黄菊：李医生下午好！上午又去做核酸监测了。<br>\n回复<br>\n赞3<br>\n7月22日 15:44<br>\nHalfiiiiisH<br>\nHalfiiiiisH：李医生下午好，希望最近有好事发生，你最近可好?<br>\n回复<br>\n赞3<br>\n7月22日 15:42<br>\n依依三一五<br>\n依依三一五：李医生，这一段日子，对于我来说太难熬了！熬过去就是重生，熬不过去就是活该！你要替我加油哦！<br>\n回复<br>\n赞2<br>\n7月22日 15:42<br>\n许仙小龙女丶<br>\n许仙小龙女丶：李医生保护我可以瘦30斤<br>\n回复<br>\n赞1<br>\n7月22日 15:42<br>\n许仙小龙女丶<br>\n许仙小龙女丶：原来大家都还记得来看李医生[悲伤]<br>\n回复<br>\n赞6<br>\n7月22日 15:41<br>\n一路上繁花似锦<br>\n一路上繁花似锦：李大夫，你好！<br>\n回复<br>\n赞<br>\n7月22日 15:39<br>\n無疾而終1013<br>\n無疾而終1013：辛巴走了。李医生，在另一个世界遇到它，帮我和它说声“对不起”好吗？是我没有把它照顾好。<br>\n回复<br>\n赞1<br>\n7月22日 15:33<br>\n小肥牛123<br>\n小肥牛123：亮哥呀，最近太闹心了，或许知识太少不懂大国担当，反正有点被人骑着头拉屎的感觉<br>\n回复<br>\n赞2<br>\n7月22日 15:32<br>\n胡同串子爱吐槽20110<br>\n胡同串子爱吐槽20110：李医生，下午好！今天是大暑节气，一年中最热的季节，愿你的家人能够平安度过。<br>\n回复<br>\n赞2<br>\n7月22日 15:31<br>\n刘乾坤<br>\n刘乾坤：下午好，今天我们这里下了暴雨<br>\n回复<br>\n赞1<br>\n7月22日 15:24<br>\n晶晶krystal1212<br>\n晶晶krystal1212：亮哥 好想知道我和他会不会有美好的结局。<br>\n回复<br>\n赞1<br>\n7月22日 15:22<br>\n行者笔记jhy<br>\n行者笔记jhy：小伙子，来看你了。<br>\n回复<br>\n赞1<br>\n7月22日 15:20<br>\nSafety宇<br>\nSafety宇：好久不见，过得还好吗？<br>\n回复<br>\n赞1<br>\n7月22日 15:15<br>\n小圆叶子欣<br>\n小圆叶子欣：没忘<br>\n回复<br>\n赞1<br>\n7月22日 15:12<br>\n未知小大人<br>\n未知小大人：李叔叔，今天高考出分，我紧张到窒息了，我一直期待自己能考好，却又怕成绩让自己失望，毕竟那么多人在等我的好消息。<br>\n回复<br>\n赞3<br>\n7月22日 15:10<br>\n是刘胖胖耶<br>\n是刘胖胖耶：李医生，你好，第一次给你留言，我们这儿挺好的，国内疫情好了很多，但是大家都一直带着口罩的，我也在开始准备自己的考研了，希望自己能够考上吧<br>\n回复<br>\n赞2<br>\n7月22日 15:09<br>\n艾--yiyi<br>\n艾--yiyi：李医生你好啊！最近过得好么？我很好哦，前段时间在股市里亏掉的钱又赚回来了，再过三个月我就要回去我的家乡了，祝我在新的生活旅程里一帆风顺永远快乐吧~，谢谢🙏🙏🙏[蜡烛][蜡烛][蜡烛]<br>\n回复<br>\n赞1<br>\n7月22日 15:07<br>\n大熊猫守护者王子<br>\n大熊猫守护者王子：今天大暑，注意防暑降温<br>\n回复<br>\n赞1<br>\n7月22日 15:06<br>\n涵菁亦楠<br>\n涵菁亦楠：李医生下午好！这周六我要参加一个会计考试，准备了有半年的时间，因为疫情一拖再拖。感觉又上班又备考还有家里的事好累好累，但我还是会努力的。<br>\n回复<br>\n赞3<br>\n7月22日 15:05<br>\n满月是只喵 等人 共3条回复<br>\n清泉石上流_14731<br>\n清泉石上流_14731：来看看你[微笑]<br>\n回复<br>\n赞2<br>\n7月22日 15:02<br>\n不一样的Magic<br>\n不一样的Magic：评论区真让人感动<br>\n回复<br>\n赞1<br>\n7月22日 14:51<br>\n思淇青<br>\n思淇青：你再优秀，也会有人把你打入冷宫；你再平凡，也会有人把你视若生命；你再善良，也得碰上知恩图报的人；你再让步，也得碰上知书达理的人。喜欢的就陪伴，讨厌的就离远，开心的就多看，伤心的就不见。掐指算算，以后还有多少时间，够我们浪费，够我们感叹。好好地活着，简单过好生命中的每一天！<br>\n回复<br>\n赞7<br>\n7月22日 14:49<br>\n思淇青<br>\n思淇青：来看看大家。经历了风风雨雨，沸沸扬扬，可我们依然每天都要来这里，说说心里话，感觉踏实。<br>\n回复<br>\n赞7<br>\n7月22日 14:47<br>\n思淇青<br>\n思淇青：今日大暑，潮湿闷热的天气，难受😣<br>\n回复<br>\n赞<br>\n7月22日 14:46<br>\nATM小额提款机<br>\nATM小额提款机：下午好李医生<br>\n回复<br>\n赞1<br>\n7月22日 14:40<br>\nlyNaaaa-<br>\nlyNaaaa-：李医生我们市还在居家隔离&nbsp; 🙁<br>\n回复<br>\n赞<br>\n7月22日 14:39<br>\n避风港zhouming<br>\n避风港zhouming：今天很热<br>\n回复<br>\n赞<br>\n7月22日 14:38<br>\n这里是1个小张呀<br>\n这里是1个小张呀：今天天气很好<br>\n回复<br>\n赞<br>\n7月22日 14:37<br>\n九七七一五<br>\n九七七一五：矮……高考要出分了，不知道会不会复读´_&gt;`我的一个朋友要去学医，希望她的未来万事胜意。<br>\n回复<br>\n赞5<br>\n7月22日 14:30<br>\n阿杨是最乖的仔<br>\n阿杨是最乖的仔：减肥好难啊！[泪]<br>\n回复<br>\n赞<br>\n7月22日 14:30<br>\n是我焦雅欣欣欣<br>\n是我焦雅欣欣欣：医生，下雨了☔️<br>\n回复<br>\n赞1<br>\n7月22日 14:30<br>\n-李-鹏<br>\n-李-鹏：下月去成都<br>\n回复<br>\n赞<br>\n7月22日 14:23<br>\n败了青柳<br>\n败了青柳：李医生中午好，最近有点迷茫，但是还是会努力生活的。希望您也过的开心愉快~<br>\n回复<br>\n赞2<br>\n7月22日 14:23<br>\n-李-鹏<br>\n-李-鹏：今日大暑&nbsp; 开始热了&nbsp; 可我在36℃的室外&nbsp; 还感觉到寒气逼人<br>\n回复<br>\n赞1<br>\n7月22日 14:23<br>\n悠悠小宝贝齐齐<br>\n悠悠小宝贝齐齐：李老师，今天大暑，你那边凉快么？记得防暑降温呦～<br>\n回复<br>\n赞1<br>\n7月22日 14:21<br>\n听闻南族有殷晚i<br>\n听闻南族有殷晚i：明天要出高考成绩了[泪]我好怕没考好[可怜]希望明天的成绩能给我一个surprise[心]拜托了<br>\n回复<br>\n赞5<br>\n7月22日 14:20<br>\n聲妹儿的架子鼓<br>\n聲妹儿的架子鼓：李医生我快递还没回来呜呜呜<br>\n回复<br>\n赞<br>\n7月22日 14:20<br>\n晓瑜儿s<br>\n晓瑜儿s：心若向阳，自然温暖[微笑]<br>\n回复<br>\n赞1<br>\n7月22日 14:16<br>\n喜爱麦子<br>\n喜爱麦子：李医生，下午好！<br>\n回复<br>\n赞<br>\n7月22日 14:12<br>\n此花非花123<br>\n此花非花123：您还在这里，大家也还没有散去，这是您离开后的第166天。我记录在这里，也把哀伤的思绪留在这里。<br>\n回复<br>\n赞3<br>\n7月22日 14:11<br>\n茴香豆儿-<br>\n茴香豆儿-：[鲜花][鲜花][鲜花][鲜花]<br>\n回复<br>\n赞<br>\n7月22日 14:10<br>\n小程要有理想<br>\n小程要有理想：我也不知道我和他还会不会遇到了，但是该相逢的人迟早会相逢的吧，我希望他过得比我好，但是还是想他能留在我身边，这样，我也过得好<br>\n回复<br>\n赞2<br>\n7月22日 14:08<br>\nMACRO1996<br>\nMACRO1996：亮哥，今天上完班就双休了。顶住，一定要顶住，咬牙[嘘][坏笑]<br>\n回复<br>\n赞2<br>\n7月22日 14:08<br>\n用户x6pov5rnmw<br>\n用户x6pov5rnmw：文亮医生！下午好<br>\n回复<br>\n赞1<br>\n7月22日 14:07<br>\n-九点三十八<br>\n-九点三十八：今天要去乐山大佛了！其实好累！<br>\n回复<br>\n赞2<br>\n7月22日 14:02<br>\n宁波LAOLI<br>\n宁波LAOLI：天气一下子就热了起来，但是很多地方的大水却没有退去。<br>\n回复<br>\n赞3<br>\n7月22日 14:01<br>\n夏天的延长线<br>\n夏天的延长线：看看你 今天大暑了 时间过的挺快<br>\n回复<br>\n赞1<br>\n7月22日 13:59<br>\n蔚蓝远山<br>\n蔚蓝远山：李叔叔 今天晚上高考出分 您一定要保我啊🙏<br>\n回复<br>\n赞5<br>\n7月22日 13:59<br>\nyu9856193<br>\nyu9856193：海口中午下了一场雨<br>\n回复<br>\n赞<br>\n7月22日 13:57<br>\n奇妙能力201801<br>\n奇妙能力201801：halo 李sir&nbsp; 昨天去医院体检年龄轻轻我就有脂肪肝了[汗]，晚上下班要去跑步+改善饮食。家人安排的第三场相亲又吹了[悲伤]，我咋就那么笨腻。<br>\n回复<br>\n赞1<br>\n7月22日 13:57<br>\nSerendipity小李小李 等人 共3条回复<br>\nCaptain_Cooper<br>\nCaptain_Cooper：看看李医生<br>\n回复<br>\n赞1<br>\n7月22日 13:53<br>\nHX-YU么<br>\nHX-YU么：总要有些随风，有些入梦，有些长留在心中<br>\n回复<br>\n赞3<br>\n7月22日 13:53<br>\nSKSA99<br>\nSKSA99：来看看你[泪]<br>\n回复<br>\n赞1<br>\n7月22日 13:49<br>\n安德烈·特尔施特根<br>\n安德烈·特尔施特根：[爱你][爱你]看看你<br>\n回复<br>\n赞3<br>\n7月22日 13:48<br>\n溢人<br>\n溢人：医生，真想让你医一下我，今天酷热，夏天的味道，<br>\n回复<br>\n赞1<br>\n7月22日 13:38<br>\n冯冯89315<br>\n冯冯89315：文亮，来看看你[可爱]无论世界多么艰难，我——都会像你样，善良的活着。想念你<br>\n回复<br>\n赞2<br>\n7月22日 13:36<br>\n琳文冉冉冉冉<br>\n琳文冉冉冉冉：李医生，今天挺热，希望你快乐[心]<br>\n回复<br>\n赞1<br>\n7月22日 13:36<br>\n暗香14329<br>\n暗香14329：你好呀<br>\n回复<br>\n赞<br>\n7月22日 13:34<br>\n柔情不蜜意<br>\n柔情不蜜意：今天大暑。 ¡评论配图<br>\n<br>\n回复<br>\n赞<br>\n7月22日 13:28<br>\n我说二爷你说耶<br>\n我说二爷你说耶：难过难过 可能虽然难 但总会过去 但是为什么要经历这么多难过呢 凭什么啊<br>\n回复<br>\n赞<br>\n7月22日 13:25<br>\n北山清泉05<br>\n北山清泉05：中午好李医生，我又复活了，千辛万苦的找到一个确信即便我怎么被封号怎么被处理对他都不会有影响的人注册了一个新号。<br>\n回复<br>\n赞2<br>\n7月22日 13:24<br>\n蓝色小鱼子<br>\n蓝色小鱼子：中午好<br>\n回复<br>\n赞<br>\n7月22日 13:17<br>\n风月-无忧<br>\n风月-无忧：我最近右眼细菌感染发炎，用药一个月了还是没好，眼皮上有个硬包怎么也消不掉，明天可能要去医院做手术清除。虽然是门诊小手术，但还是有点害怕，四年前左眼类似情况做过一次手术心里有阴影。对了，上次在<mark>支</mark>付宝挂眼科号，给我推荐到武汉中心医院去了，我又手动输入的合肥医院，我不在武汉啊，好奇怪。<br>\n回复<br>\n赞1<br>\n7月22日 13:16<br>\n蓝色小鱼子 等人 共3条回复<br>\n晶晶krystal1212<br>\n晶晶krystal1212：那个一想起来就发自内心不自觉笑的人，应该很爱很爱吧。大学毕业后又遇到了大学同学。<br>\n回复<br>\n赞1<br>\n7月22日 13:11<br>\n肛肠科护士<br>\n肛肠科护士：李医生您好：中午食堂菜茄子，花菜有小虫子恶心。<br>\n回复<br>\n赞2<br>\n7月22日 13:08<br>\n试试会不会重名<br>\n试试会不会重名：致良知！<br>\n回复<br>\n赞2<br>\n7月22日 13:06<br>\n蓝Len蓝蓝Len<br>\n蓝Len蓝蓝Len：李先生[蜡烛]<br>\n回复<br>\n赞<br>\n7月22日 13:05<br>\n枫兄这名字居然也有人用<br>\n枫兄这名字居然也有人用：午安，文亮兄<br>\n回复<br>\n赞2<br>\n7月22日 13:00<br>\nZicon_<br>\nZicon_：李医生好<br>\n回复<br>\n赞1<br>\n7月22日 12:57<br>\n空气炮-<br>\n空气炮-：祖国不会忘记<br>\n回复<br>\n赞<br>\n7月22日 12:51<br>\n我不知道应该起什么昵称_<br>\n我不知道应该起什么昵称_：李医生中午好<br>\n回复<br>\n赞<br>\n7月22日 12:49<br>\n葡萄籽先生<br>\n葡萄籽先生：i dont know why<br>\n回复<br>\n赞<br>\n7月22日 12:48<br>\n郑才怪船长<br>\n郑才怪船长：中午好<br>\n回复<br>\n赞1<br>\n7月22日 12:46<br>\n沙耳尼123<br>\n沙耳尼123：好快的日子啊<br>\n回复<br>\n赞<br>\n7月22日 12:42<br>\nlasemayi<br>\nlasemayi：够忙的<br>\n回复<br>\n赞<br>\n7月22日 12:42<br>\n今天当一只咸鱼<br>\n今天当一只咸鱼：李医生，怎么说呢，我可能要下岗了不过好消息是有补偿金，也行了。那个家伙太傻了，性格多疑，能力差，不懂还特别死拧，给别人添乱，我实在忍不了骂了他，走就走吧。李医生你现在咋样啊？<br>\n回复<br>\n赞7<br>\n7月22日 12:35<br>\nBlackFootedCat<br>\nBlackFootedCat：李医生，丁香园关于新疆出现疫情的文章被删了，同样的故事现在又在新疆上演<br>\n回复<br>\n赞9<br>\n7月22日 12:35<br>\n晒脸大赛第一名<br>\n晒脸大赛第一名：李医生，你说生活怎么这么难啊<br>\n回复<br>\n赞2<br>\n7月22日 12:34<br>\nbluefox1024<br>\nbluefox1024：手鸡腿好吃<br>\n回复<br>\n赞<br>\n7月22日 12:31<br>\n首阳山上的小靖子<br>\n首阳山上的小靖子：[心][心][心]<br>\n回复<br>\n赞<br>\n7月22日 12:29<br>\nNocturne宇<br>\nNocturne宇：老李、我说过今年要来武汉看你、我今天已经来了、你在哪啊[泪][泪][泪]<br>\n回复<br>\n赞3<br>\n7月22日 12:27<br>\n九思无误<br>\n九思无误：中午<br>\n回复<br>\n赞1<br>\n7月22日 12:26<br>\n仙人球9820<br>\n仙人球9820：记得，向上而行，等待对的时间到来 GOD BLESS US<br>\n回复<br>\n赞1<br>\n7月22日 12:24<br>\nLWL-FD<br>\nLWL-FD：李医生，能看看我的🏠巢湖吗？<br>\n回复<br>\n赞1<br>\n7月22日 12:23<br>\n最最好的那朵云<br>\n最最好的那朵云：李医生，你好，时隔了半年，我有男朋友了。我想我应该完完整整的从上一段感情的阴影中走出来了。以前我总是懂事又体贴，生怕对方不开心，现在终于遇到一个人，他温柔体贴又懂我，他教我做小孩子，而且高高帅帅的，是理想版的未来老公的样子。祝我幸福吧。李医生。下一次我来留言的时候希望我已经结婚了<br>\n回复<br>\n赞13<br>\n7月22日 12:16<br>\n草莓味的嘎吱脆yr 等人 共7条回复<br>\n桃花岛主哥<br>\n桃花岛主哥：过来看看你，希望一切慢慢变好。<br>\n回复<br>\n赞2<br>\n7月22日 12:14<br>\n云朵儿娜<br>\n云朵儿娜：李医生，你说生活怎么这么难啊<br>\n回复<br>\n赞<br>\n7月22日 12:12<br>\n胡章鸿<br>\n胡章鸿：说得好！//@天有何問: 所谓的正能量到底是个什么东西？我们如果不去保护人们心中的善意，那么正能量又有何意义。国家本身是没有善意的，它是冷冰冰的机器，构成这国家的一个个鲜活的人所传递的温度才是我们团结的价值。如果有人因悲愤而报复社会，比解决罪犯更重要的是解决悲愤的源头。一颗心的<br>\n回复<br>\n赞3<br>\n7月22日 12:12<br>\n最佳佳佳损友_<br>\n最佳佳佳损友_：李医生 武汉又夏天了 替你高兴还有这么多人在记得你<br>\n回复<br>\n赞7<br>\n7月22日 12:07<br>\n小仙女甜甜甜<br>\n小仙女甜甜甜：李医生，好久没来看你了，我的生活依然很糟糕，可是还是要坚持<br>\n回复<br>\n赞2<br>\n7月22日 12:05<br>\n不困真可爱<br>\n不困真可爱：李医生 最近又在好好生活了<br>\n回复<br>\n赞2<br>\n7月22日 12:01<br>\n王大拿哒哒哒<br>\n王大拿哒哒哒：李医生你好&nbsp; 你在那边过得很好吧&nbsp; 吃炸鸡了吗 [加油]我马上就好手术了&nbsp; 请保佑我一切顺利<br>\n回复<br>\n赞3<br>\n7月22日 12:00<br>\n关山一万年<br>\n关山一万年：李医生 我明天出成绩啦 希望我能去想去的大学<br>\n回复<br>\n赞4<br>\n7月22日 12:00<br>\n英子來年書 等人 共2条回复<br>\n小浣熊豆豆奇多<br>\n小浣熊豆豆奇多：李医生，haruma也离开我们了。我暂时还放不下这件事，想在您这里躲一会。<br>\n回复<br>\n赞3<br>\n7月22日 12:00<br>\nyuanzhi流年<br>\nyuanzhi流年：李医生 你好。今日大暑，天气变得越来越热了。<br>\n回复<br>\n赞1<br>\n7月22日 11:59<br>\n你想堆一个雪怪吗<br>\n你想堆一个雪怪吗：李医生你好，我有工作了。<br>\n回复<br>\n赞3<br>\n7月22日 11:57<br>\n婧婧元元<br>\n婧婧元元：午安<br>\n回复<br>\n赞5<br>\n7月22日 11:51<br>\n社员都是向阳花2003<br>\n社员都是向阳花2003：李医生，做人真难，人间真的不值得，期望没有来生，好想消失在茫茫宇宙之中，可是还有牵挂，还有羁绊，还有担忧，人生不是自己的，真难。<br>\n回复<br>\n赞2<br>\n7月22日 11:50<br>\n婧婧元元 等人 共1条回复<br>\nDangdang的啦<br>\nDangdang的啦：李医生 好久没来看你了，你好嘛<br>\n回复<br>\n赞4<br>\n7月22日 11:48<br>\n彰德府的小仙女<br>\n彰德府的小仙女：我马上要省考了，后面还有一系列的考试，有点累，你最近给人看病累不累啊<br>\n回复<br>\n赞<br>\n7月22日 11:47<br>\n爱吃西红柿炒鸡蛋1<br>\n爱吃西红柿炒鸡蛋1：李医生 你好<br>\n回复<br>\n赞1<br>\n7月22日 11:42<br>\n车牌648320<br>\n车牌648320：中午好李医生，今天35度，如果你在，世界将多么美好。<br>\n回复<br>\n赞4<br>\n7月22日 11:41<br>\n共1条回复<br>\niamcouplefan<br>\niamcouplefan：[鮮花]<br>\n回复<br>\n赞2<br>\n7月22日 11:39<br>\n共1条回复<br>\n酒剑仙人桃花妖<br>\n酒剑仙人桃花妖：中午好呀~<br>\n回复<br>\n赞1<br>\n7月22日 11:33<br>\n夏永红610103196606033671 等人 共1条回复<br>\n燕姿迷弟<br>\n燕姿迷弟：中午好<br>\n回复<br>\n赞1<br>\n7月22日 11:32<br>\n共1条回复<br>\n小李目标瘦十斤<br>\n小李目标瘦十斤：亮哥，今天又下雨了，好大好大的雨，今年雨特别多，亮哥，想你了<br>\n回复<br>\n赞1<br>\n7月22日 11:31<br>\n共1条回复<br>\n泡面君YS<br>\n泡面君YS：李医生，保佑我能顺利上岸吧，谢谢您<br>\n回复<br>\n赞2<br>\n7月22日 11:31<br>\n夏永红610103196606033671 等人 共1条回复<br>\n斯外蹬<br>\n斯外蹬：哥 该吃午饭了<br>\n回复<br>\n赞3<br>\n7月22日 11:30<br>\n共1条回复<br>\n八景上<br>\n八景上：[二哈]<br>\n回复<br>\n赞1<br>\n7月22日 11:27<br>\nSerendipity小李小李<br>\nSerendipity小李小李：哥 最近遇到了一个有好感的男孩子 我很久没有遇到让自己心动的人了 好喜欢<br>\n回复<br>\n赞5<br>\n7月22日 11:25<br>\n斯外蹬 等人 共2条回复<br>\n咬人奇奇酱ii<br>\n咬人奇奇酱ii：16岁创业真的太难了太难了[doge]难到想放弃<br>\n回复<br>\n赞2<br>\n7月22日 11:20<br>\n最近叫a-tan<br>\n最近叫a-tan：哥，我好累啊。今天上午物流把货丢在楼下，我徒手搬了16趟，才把地板贴搬上楼。 创业真心不易，有点想哭。仿佛也没有能说的人[失望]<br>\n回复<br>\n赞4<br>\n7月22日 11:19<br>\n填Ssmile<br>\n填Ssmile：中午好！该吃饭了<br>\n回复<br>\n赞1<br>\n7月22日 11:18","date":"2020-07-24","agreeCount":0,"discussionCount":0}