{"type":"answer","id":25489,"parentType":"question","parentId":6137,"uid":3811,"contents":"<s>Hello Hawaii</s>&nbsp;Havana<br>\n<a href=\"https://www.youtube.com/watch?v=74gx0v5ZJzw\" rel=\"nofollow noreferrer noopener\" target=\"_blank\">https://www.youtube.com/watch?v=74gx0v5ZJzw</a><br>\n<br>\nAll I Want For Christmas Is You<br>\n<a href=\"https://www.youtube.com/watch?v=KWNm2VM6YDM\" rel=\"nofollow noreferrer noopener\" target=\"_blank\">https://www.youtube.com/watch?v=KWNm2VM6YDM</a>","date":"2019-12-04","agreeCount":5,"discussionCount":1}