{"type":"article_comment","id":14512,"parentType":"article","parentId":2318,"uid":6382,"contents":"<a href=\"https://i.redd.it/d0ccdoqail451.jpg\" rel=\"nofollow noreferrer noopener\" target=\"_blank\"><img src=\"https://i.redd.it/d0ccdoqail451.jpg\" alt=\"https://i.redd.it/d0ccdoqail451.jpg\" style=\"max-width:100%\"></a><br>\n想起那个在红场门口发白纸被抓的政治笑话了，克格勃说“谁都知道你这个白纸上要写什么东西”<br>\n<a href=\"https://i.redd.it/mtm9jeoail451.jpg\" rel=\"nofollow noreferrer noopener\" target=\"_blank\"><img src=\"https://i.redd.it/mtm9jeoail451.jpg\" alt=\"https://i.redd.it/mtm9jeoail451.jpg\" style=\"max-width:100%\"></a><br>\n可怕，看来中国未来管制的不仅仅是外汇，就连现金都跟着管，下一步中国政府还打算怎么割民众韭菜？","date":"2020-06-13","agreeCount":2,"discussionCount":0}