{"type":"question","id":10631,"title":"上海高考出卷老师里是不是有内鬼？","uid":7292,"topics":[14,2589],"contents":"<a href=\"https://i.imgur.com/LGJPJ7u.jpg\" rel=\"nofollow noreferrer noopener\" target=\"_blank\"><img src=\"https://i.imgur.com/LGJPJ7u.jpg\" alt=\"https://i.imgur.com/LGJPJ7u.jpg\" style=\"max-width:100%\"></a><br>\n如果我们的铁骑继续前进，这个螳臂当车的歹徒……<br>\n<br>\n“如果中国有朝一日变了颜色，变成一个超级大国，也在世界上称王称霸，到处欺负人家，侵略人家，剥削人民，人民就应当给中国戴上一顶社会帝国主义的帽子，就应当揭露它，反对它，并且同中国人民一道，打倒它。“<br>\n<br>\n还有香港国安法我也能套题……<br>\n草<br>\n不过各位可以期待一下，明天我会把上海高考作文的膜包精甚版写出来。","date":"2020-07-08","agreeCount":19,"discussionCount":0}