{"type":"question","id":14327,"title":"（非作死）又有新的8964车牌出现了！（又更新了两个）","uid":8437,"topics":[469,541,754],"contents":"<a href=\"https://pbs.twimg.com/media/Etcfe2qUcAAi0AF?format=jpg&amp;name=large\" rel=\"nofollow noreferrer noopener\" target=\"_blank\"></a><a href=\"https://pbs.twimg.com/media/Etcfe2qUcAAi0AF?format=jpg&amp;name=large\" rel=\"nofollow noreferrer noopener\" target=\"_blank\"><img src=\"https://pbs.twimg.com/media/Etcfe2qUcAAi0AF?format=jpg&amp;name=large\" alt=\"https://pbs.twimg.com/media/Etcfe2qUcAAi0AF?format=jpg&amp;name=large\" style=\"max-width:100%\"></a><br>\n<br>\n<a href=\"https://pbs.twimg.com/media/EtcpDhqVoAAILOC?format=jpg&amp;name=large\" rel=\"nofollow noreferrer noopener\" target=\"_blank\"><img src=\"https://pbs.twimg.com/media/EtcpDhqVoAAILOC?format=jpg&amp;name=large\" alt=\"https://pbs.twimg.com/media/EtcpDhqVoAAILOC?format=jpg&amp;name=large\" style=\"max-width:100%\"></a><br>\n<br>\n<a href=\"https://pbs.twimg.com/media/EtehdHJVEAATAZp?format=jpg&amp;name=large\" rel=\"nofollow noreferrer noopener\" target=\"_blank\"><img src=\"https://pbs.twimg.com/media/EtehdHJVEAATAZp?format=jpg&amp;name=large\" alt=\"https://pbs.twimg.com/media/EtehdHJVEAATAZp?format=jpg&amp;name=large\" style=\"max-width:100%\"></a><br>\n<br>\n<a href=\"https://pbs.twimg.com/media/EtjFwbjU0AEFkz8?format=jpg&amp;name=large\" rel=\"nofollow noreferrer noopener\" target=\"_blank\"><img src=\"https://pbs.twimg.com/media/EtjFwbjU0AEFkz8?format=jpg&amp;name=large\" alt=\"https://pbs.twimg.com/media/EtjFwbjU0AEFkz8?format=jpg&amp;name=large\" style=\"max-width:100%\"></a><br>\n前 情 提 要 ：<br>\n<a href=\"https://pbs.twimg.com/media/EtcffNJVcAk5rDz?format=jpg&amp;name=large\" rel=\"nofollow noreferrer noopener\" target=\"_blank\"><img src=\"https://pbs.twimg.com/media/EtcffNJVcAk5rDz?format=jpg&amp;name=large\" alt=\"https://pbs.twimg.com/media/EtcffNJVcAk5rDz?format=jpg&amp;name=large\" style=\"max-width:100%\"></a><br>\n<br>\n下次是不是连车牌也打码了？<br>\n这种IP地址是不是也该收回了？<br>\n(“主机名”是虚构的，请勿尝试无VPN状态下ping或是traceroute，防止被拉清单！）<br>\n不过我觉得没有人会吃饱了没事干，手动把那个主机名打出来，，，<br>\n<a href=\"https://iili.io/fTQ4Fj.png\" rel=\"nofollow noreferrer noopener\" target=\"_blank\"><img src=\"https://iili.io/fTQ4Fj.png\" alt=\"https://iili.io/fTQ4Fj.png\" style=\"max-width:100%\"></a>","date":"2021-02-06","agreeCount":7,"discussionCount":0}