{"type":"question","id":1995,"title":"坊间传言：聂树斌被枪毙是为了换器官给章含之，是真是假？","uid":1564,"topics":[5073],"contents":"注意到章含之女儿洪晃（姜文老婆）的解释有前后矛盾之处：一方面说，我们不清楚器官来源；另一方面又说，但我确定那不是来自聂树斌的。<br>\n<br>\n执行死刑时间确凿是冬天，和章含之手术时间一致，而官方则欲盖弥彰，说是5月执行的。<a href=\"https://mhimg.github.io/ueditor/20180720/1532056538735522.jpg\" rel=\"nofollow noreferrer noopener\" target=\"_blank\"><img src=\"https://mhimg.github.io/ueditor/20180720/1532056538735522.jpg\" alt=\"https://mhimg.github.io/ueditor/20180720/1532056538735522.jpg\" style=\"max-width:100%\"></a>","date":"2018-07-20","agreeCount":4,"discussionCount":0}