{"type":"question","id":5823,"title":"如何看待部分品葱用户提出的《膜犯引渡条例》？","uid":16,"topics":[8,10,678,855,2112],"contents":"近日（近平的近，炕日的日，这是坠痛苦的），有品葱用户提议江膜乎并入品葱，并派出专员前往膜乎<a href=\"https://mohu.pincong.rocks/article/742\" rel=\"nofollow noreferrer noopener\" target=\"_blank\">张贴草案，展开公众咨询</a>。<br>\n<br>\n虽然大哥两头表态，权威发布，但是依旧有部分建制派黄红黄丝兹磁并入品葱同意乳包。<br>\n<br>\n我把这个编辑成一个问题，这样得票坠高的回答就会被挂在坠上方，而不是像那篇送葱草案是文章格式，大哥的答案被压在很下面。<br>\n<br>\n我先来！<br>\n<br>\n<b>光复膜乎，时代革命！膜乎人加油！</b>","date":"2019-11-17","agreeCount":20,"discussionCount":0}