{"type":"question","id":6706,"title":"做包子表情包时被妹妹看到了","uid":4881,"topics":[6,220,318,903],"contents":"&nbsp; &nbsp; &nbsp; &nbsp; 她说：“你这样不太好吧，这样是不尊重领导人。”<br>\n&nbsp; &nbsp; &nbsp; &nbsp; 我就讲：“哪里……这最多也只是调侃。”<br>\n&nbsp; &nbsp; &nbsp; &nbsp; “可他是主席啊。”<br>\n&nbsp; &nbsp; &nbsp; &nbsp; “江泽民同志也是主席，膜蛤文化不是很广传吗？”<br>\n&nbsp; &nbsp; &nbsp; &nbsp; “膜蛤是啥？”<br>\n&nbsp; &nbsp; &nbsp; &nbsp; “算了…有些东西，不要知道得太多。”<br>\n&nbsp; &nbsp; &nbsp; &nbsp; “那你干嘛要去了解？不会只有你知道吧？”<br>\n&nbsp; &nbsp; &nbsp; &nbsp; “太多人知道这个了。”<br>\n&nbsp; &nbsp; &nbsp; &nbsp; “别人去了解你就得去了解吗？那既然很多人了解，为什么我的同学不了解呢？”<br>\n&nbsp; &nbsp; &nbsp; &nbsp; “你是不是不知道有个东西叫墙……”<br>\n&nbsp; &nbsp; &nbsp; &nbsp; 她便露出一股不耐烦的神色。<br>\n&nbsp; &nbsp; &nbsp; &nbsp; “我跟你说啊，有些东西，真的不能去了解。如果太多人了解了，对国家治理不好。国家为了这个社会安定呢，就设了墙，有了墙，中国的人民就不能看到反动的东西，除非翻墙，也就是用VPN之类。”<br>\n&nbsp; &nbsp; &nbsp; &nbsp; “好好好。但习主席他也做过一些贡献的。”<br>\n&nbsp; &nbsp; &nbsp; &nbsp; 说到贡献，我脑子里想到的首先却是修宪的事，便讲给她听，说是包子要做皇帝啊，开历史倒车啊。<br>\n&nbsp; &nbsp; &nbsp; &nbsp; “如果他搞这些是不好的，那肯定没人会支持的，但他做的一般都是有很多人支持的。”<br>\n&nbsp; &nbsp; &nbsp; &nbsp; “我再说一遍，有个东西叫墙…”<br>\n&nbsp; &nbsp; &nbsp; &nbsp; “好好好好。”然后她就不厌烦地，趴头玩起手机来。<br>\n<br>\n<br>\n<br>\n&nbsp; &nbsp; &nbsp; &nbsp; 请问要怎样教导我的妹妹呢？<br>\n&nbsp; &nbsp; &nbsp; &nbsp; 还是看她年龄尚小（小学六年级），不要讲这些为好？","date":"2020-01-05","agreeCount":30,"discussionCount":11}