{"type":"article_comment","id":23364,"parentType":"article","parentId":3216,"uid":8194,"contents":"2047的用户个人页面可以放置任意帖子或回复，起到个人简介的作用。比如说&nbsp;<a href=\"https://2047.name/u/3393\" rel=\"nofollow noreferrer noopener\" target=\"_blank\">https://2047.name/u/3393</a><br>\n<br>\n2047支持youtube链接自动转youtube视频播放。<br>\n<br>\n2047支持在帖子内快速引用站内其他帖子，例如 &lt;t4100&gt; 等效于 &lt;a href='/t/4100'&gt;/t/4100&lt;/a&gt;，非常方便。<br>\n<br>\n2047支持在帖子中 @ 用户，被@ 的人会收到一个提醒，如果帖子中漏了@ 某个人，只需要修改帖子补充进去，系统就会自动补充提醒。<br>\n<br>\n2047用户可以给任何人发小纸条。<br>\n<br>\n关注还没做，todolist很长，争取尽快做好。","date":"2020-08-27","agreeCount":2,"discussionCount":0}